matrix-sydent.service
sydent/__init__.py
sydent/config/__init__.py
sydent/config/_base.py
sydent/config/crypto.py
sydent/config/database.py
sydent/config/email.py
sydent/config/exceptions.py
sydent/config/general.py
sydent/config/http.py
sydent/config/sms.py
sydent/db/__init__.py
sydent/db/accounts.py
sydent/db/hashing_metadata.py
sydent/db/invite_tokens.py
sydent/db/invite_tokens.sql
sydent/db/peers.py
sydent/db/peers.sql
sydent/db/sqlitedb.py
sydent/db/terms.py
sydent/db/threepid_associations.py
sydent/db/threepid_associations.sql
sydent/db/threepid_validation.sql
sydent/db/valsession.py
sydent/hs_federation/__init__.py
sydent/hs_federation/types.py
sydent/hs_federation/verifier.py
sydent/http/__init__.py
sydent/http/auth.py
sydent/http/blacklisting_reactor.py
sydent/http/federation_tls_options.py
sydent/http/httpclient.py
sydent/http/httpcommon.py
sydent/http/httpsclient.py
sydent/http/httpserver.py
sydent/http/matrixfederationagent.py
sydent/http/servlets/__init__.py
sydent/http/servlets/accountservlet.py
sydent/http/servlets/authenticated_bind_threepid_servlet.py
sydent/http/servlets/authenticated_unbind_threepid_servlet.py
sydent/http/servlets/blindlysignstuffservlet.py
sydent/http/servlets/bulklookupservlet.py
sydent/http/servlets/cors_servlet.py
sydent/http/servlets/emailservlet.py
sydent/http/servlets/getvalidated3pidservlet.py
sydent/http/servlets/hashdetailsservlet.py
sydent/http/servlets/logoutservlet.py
sydent/http/servlets/lookupservlet.py
sydent/http/servlets/lookupv2servlet.py
sydent/http/servlets/msisdnservlet.py
sydent/http/servlets/pubkeyservlets.py
sydent/http/servlets/registerservlet.py
sydent/http/servlets/replication.py
sydent/http/servlets/store_invite_servlet.py
sydent/http/servlets/termsservlet.py
sydent/http/servlets/threepidbindservlet.py
sydent/http/servlets/threepidunbindservlet.py
sydent/http/servlets/versions.py
sydent/http/srvresolver.py
sydent/replication/__init__.py
sydent/replication/peer.py
sydent/replication/pusher.py
matrix_sydent-2.6.1.dist-info/LICENSE
matrix_sydent-2.6.1.dist-info/METADATA
matrix_sydent-2.6.1.dist-info/WHEEL
matrix_sydent-2.6.1.dist-info/entry_points.txt
matrix_sydent-2.6.1.dist-info/RECORD
