Metadata-Version: 2.1
Name: matrix-sydent
Version: 2.6.1
Summary: Reference Matrix Identity Verification and Lookup Server
Home-page: https://github.com/matrix-org/sydent
License: Apache-2.0
Author: Matrix.org Team and Contributors
Author-email: packages@matrix.org
Requires-Python: >=3.7,<4.0
Classifier: Development Status :: 5 - Production/Stable
Classifier: License :: OSI Approved :: Apache Software License
Classifier: Programming Language :: Python :: 3
Classifier: Programming Language :: Python :: 3.7
Classifier: Programming Language :: Python :: 3.8
Classifier: Programming Language :: Python :: 3.9
Classifier: Programming Language :: Python :: 3.10
Classifier: Programming Language :: Python :: 3.11
Classifier: Programming Language :: Python :: 3.12
Provides-Extra: prometheus
Provides-Extra: sentry
Requires-Dist: attrs (>=19.1.0)
Requires-Dist: jinja2 (>=3.0.0)
Requires-Dist: matrix-common (>=1.1.0,<2.0.0)
Requires-Dist: netaddr (>=0.7.0)
Requires-Dist: phonenumbers (>=8.12.32)
Requires-Dist: prometheus-client (>=0.4.0) ; extra == "prometheus"
Requires-Dist: pyOpenSSL (>=16.0.0)
Requires-Dist: pynacl (>=1.2.1)
Requires-Dist: pyyaml (>=3.11)
Requires-Dist: sentry-sdk (>=0.7.2) ; extra == "sentry"
Requires-Dist: service-identity (>=1.0.0)
Requires-Dist: signedjson (==1.1.1)
Requires-Dist: sortedcontainers (>=2.1.0)
Requires-Dist: twisted (>=18.4.0)
Requires-Dist: typing-extensions (>=3.7.4)
Requires-Dist: unpaddedbase64 (>=1.1.0)
Requires-Dist: zope.interface (>=4.6.0)
Project-URL: Repository, https://github.com/matrix-org/sydent
